{
    "url": {
        "data": "http:\/\/cdcb.judicial.gov.tw\/abbs\/wkw\/WHD6K03.jsp?ab=AAAdkxAAHAAAPN%2BAAB&bc=108&cd=%AA%6B%B5%6E%AA%C0++++++++++++++&de=000004&ef=CYD&fg=1",
        "staff": "http:\/\/cdcb.judicial.gov.tw\/abbs\/wkw\/WHD6K04.jsp?ab=AAAdkxAAHAAAPN%2BAAB&bc=108&cd=%AA%6B%B5%6E%AA%C0++++++++++++++&de=000004&ef=CYD&fg=1",
        "office": "http:\/\/cdcb.judicial.gov.tw\/abbs\/wkw\/WHD6K07.jsp?ab=AAAdkxAAHAAAPN%2BAAB&bc=108&cd=%AA%6B%B5%6E%AA%C0++++++++++++++&de=000004&ef=CYD&fg=1"
    },
    "登記案號": "108年法登社字4號",
    "類別": "社團",
    "案由": "設立登記",
    "主任": "陳雪芬",
    "登記號數": "609",
    "收件日期": "108\/05\/27",
    "登記日期": "108\/05\/28",
    "公告日期": "108\/05\/28",
    "登記簿": "20冊11頁",
    "任期判定": "",
    "屆期判定": "",
    "法人代表": "周柏宏",
    "法人名稱": "社團法人台灣腦性麻痺休閒運動協會",
    "設立登記日期": "108\/05\/28",
    "主事務所": "嘉義市西區泰山二街32號",
    "目的": "以結合社會各界之力量，協助腦性麻痺者參與休閒運動、學習生活獨立，適應社會生活為宗旨。",
    "捐助方法": "會費、捐款、其他收入等",
    "許可機關日期": "內政部中華民國107年4月16日台內團字第1070012078號函",
    "存立時期": "永久",
    "財產總額": "",
    "結案原因": "准許",
    "結案日期": "108\/05\/28",
    "歸檔日期": "",
    "發證日期": "",
    "送達代收人姓名": "",
    "送達代收人住址": "",
    "郵遞區號": "",
    "清算人": "",
    "註銷日期": "",
    "撤銷日期": "",
    "撤(註)銷機關文號": "",
    "撤(註)銷原因": "",
    "董監事": [
        [
            "理事長",
            "周柏宏"
        ],
        [
            "常務理事",
            "吳汀原"
        ],
        [
            "常務理事",
            "許姿雅"
        ],
        [
            "理事",
            "李斐可"
        ],
        [
            "理事",
            "陳慧芬"
        ],
        [
            "理事",
            "王銘槿"
        ],
        [
            "理事",
            "李旺澈"
        ],
        [
            "理事",
            "鄭建宏"
        ],
        [
            "理事",
            "蔡美惠"
        ],
        [
            "常務監事",
            "顏簡素真"
        ],
        [
            "監事",
            "陳俐俐"
        ],
        [
            "監事",
            "黃建智"
        ]
    ],
    "分事務所": [],
    "latitude": "",
    "longitude": ""
}