{
    "url": {
        "data": "http:\/\/cdcb.judicial.gov.tw\/abbs\/wkw\/WHD6K03.jsp?ab=AAAdkxAAHAAAPItAAK&bc=107&cd=%AA%6B%B5%6E%A5%4C++++++++++++++&de=001262&ef=TPD&fg=2",
        "staff": "http:\/\/cdcb.judicial.gov.tw\/abbs\/wkw\/WHD6K04.jsp?ab=AAAdkxAAHAAAPItAAK&bc=107&cd=%AA%6B%B5%6E%A5%4C++++++++++++++&de=001262&ef=TPD&fg=2",
        "office": "http:\/\/cdcb.judicial.gov.tw\/abbs\/wkw\/WHD6K07.jsp?ab=AAAdkxAAHAAAPItAAK&bc=107&cd=%AA%6B%B5%6E%A5%4C++++++++++++++&de=001262&ef=TPD&fg=2"
    },
    "登記案號": "107年法登他字1262號",
    "類別": "社團",
    "案由": "變更登記",
    "主任": "楊志純",
    "登記號數": "2320",
    "收件日期": "107\/09\/05",
    "登記日期": "107\/09\/27",
    "公告日期": "107\/09\/27",
    "登記簿": "106冊61頁",
    "任期判定": "2",
    "屆期判定": "",
    "法人代表": "徐錦鋒",
    "法人名稱": "社團法人中華民國觀護協會",
    "設立登記日期": "102\/07\/15",
    "主事務所": "台北市萬華區成都路117號6樓",
    "目的": "以結合社會力量，貢獻智能，研究觀護學術，宏揚觀護制度，推廣觀護事業，協助政府辦理觀護輔導工作，促進安和樂利之社會與福利，及參加國際交流活動為宗旨。",
    "捐助方法": "個人（團體）會員之入會費及常年會費、自由捐贈、政府補助、基金孳息、其他收入",
    "許可機關日期": "內政部中華民國102年7月2日台內社字第1020245925號函",
    "存立時期": "永久",
    "財產總額": "200000",
    "結案原因": "准許",
    "結案日期": "107\/09\/27",
    "歸檔日期": "",
    "發證日期": "107\/10\/05",
    "送達代收人姓名": "",
    "送達代收人住址": "",
    "郵遞區號": "",
    "清算人": "",
    "註銷日期": "",
    "撤銷日期": "",
    "撤(註)銷機關文號": "",
    "撤(註)銷原因": "",
    "董監事": [
        [
            "副理事長",
            "徐素真"
        ],
        [
            "理事",
            "林長亨"
        ],
        [
            "理事長",
            "徐錦鋒"
        ],
        [
            "常務理事",
            "陳正德"
        ],
        [
            "常務監事召集人",
            "陳阿鳳"
        ],
        [
            "常務監事",
            "黃憲鐘"
        ],
        [
            "理事",
            "陳火炎"
        ],
        [
            "理事",
            "高永吉"
        ],
        [
            "常務理事",
            "陳金海"
        ],
        [
            "副理事長",
            "李榮昌"
        ],
        [
            "監事",
            "許泗淮"
        ],
        [
            "常務理事",
            "王茄明"
        ],
        [
            "理事",
            "羅頌杰"
        ],
        [
            "理事",
            "李文森"
        ],
        [
            "理事",
            "簡崇吉"
        ],
        [
            "理事",
            "翁正印"
        ],
        [
            "副理事長",
            "張三華"
        ],
        [
            "理事",
            "黃錫杕"
        ],
        [
            "理事",
            "楊碧玉"
        ],
        [
            "理事",
            "許溫德"
        ],
        [
            "理事",
            "柯富騰"
        ],
        [
            "理事",
            "廖建程"
        ],
        [
            "監事",
            "羅秀芬"
        ],
        [
            "理事",
            "郭葉青"
        ],
        [
            "理事",
            "周淑媛"
        ],
        [
            "理事",
            "黃武田"
        ],
        [
            "理事",
            "韓麗卿"
        ],
        [
            "常務理事",
            "黃瓊徵"
        ],
        [
            "常務監事",
            "翁美雯"
        ],
        [
            "理事",
            "林文隆"
        ],
        [
            "理事",
            "張維清"
        ],
        [
            "監事",
            "周崾成"
        ],
        [
            "常務理事",
            "陳君儀"
        ],
        [
            "理事",
            "林宏興"
        ],
        [
            "理事",
            "蔡惠如"
        ],
        [
            "理事",
            "余顀山"
        ],
        [
            "監事",
            "許哲政"
        ],
        [
            "常務理事",
            "康麗娟"
        ],
        [
            "常務理事",
            "林金鎮"
        ],
        [
            "監事",
            "徐慶忠"
        ],
        [
            "監事",
            "楊茗莉"
        ],
        [
            "監事",
            "鄭培元"
        ],
        [
            "理事",
            "楊司平"
        ],
        [
            "理事",
            "簡明珠"
        ],
        [
            "監事",
            "顏進森"
        ],
        [
            "理事",
            "張秀珠"
        ]
    ],
    "分事務所": [],
    "latitude": "",
    "longitude": ""
}