{
    "url": {
        "data": "http:\/\/cdcb.judicial.gov.tw\/abbs\/wkw\/WHD6K03.jsp?ab=AAAdkxAAHAAAPI%2BAAB&bc=107&cd=%AA%6B%B5%6E%A5%4C++++++++++++++&de=001444&ef=TPD&fg=1",
        "staff": "http:\/\/cdcb.judicial.gov.tw\/abbs\/wkw\/WHD6K04.jsp?ab=AAAdkxAAHAAAPI%2BAAB&bc=107&cd=%AA%6B%B5%6E%A5%4C++++++++++++++&de=001444&ef=TPD&fg=1",
        "office": "http:\/\/cdcb.judicial.gov.tw\/abbs\/wkw\/WHD6K07.jsp?ab=AAAdkxAAHAAAPI%2BAAB&bc=107&cd=%AA%6B%B5%6E%A5%4C++++++++++++++&de=001444&ef=TPD&fg=1"
    },
    "": null,
    "法人登記資料": "登記案號",
    "董監事": [
        [
            "董事",
            "鄭依潔"
        ],
        [
            "董事",
            "鄭慧价"
        ],
        [
            "常務董事",
            "鄭秋松"
        ],
        [
            "董事",
            "鄭資豊"
        ],
        [
            "董事長",
            "鄭憲和"
        ],
        [
            "常務董事",
            "鄭誌鵬"
        ],
        [
            "常務董事",
            "鄭克志"
        ],
        [
            "董事",
            "鄭元宏"
        ],
        [
            "監事",
            "鄭林玉珠"
        ],
        [
            "常務董事",
            "鄭水誠"
        ],
        [
            "常務監事",
            "鄭輝華"
        ],
        [
            "監事",
            "楊春山"
        ]
    ],
    "分事務所": [],
    "latitude": "",
    "longitude": ""
}